<?xml version="1.0" encoding="utf-8" ?><dwsync><file name="Base64ContentEncoder.php" server="ftp.mercedesbenzmx.com" local="3500626666" remote="318763443893966832" Dst="-1" /><file name="NativeQpContentEncoder.php" server="ftp.mercedesbenzmx.com" local="3500626666" remote="318763443893966832" Dst="-1" /><file name="PlainContentEncoder.php" server="ftp.mercedesbenzmx.com" local="3500626666" remote="318763443893966832" Dst="-1" /><file name="QpContentEncoder.php" server="ftp.mercedesbenzmx.com" local="3500626666" remote="318763443893966832" Dst="-1" /><file name="QpContentEncoderProxy.php" server="ftp.mercedesbenzmx.com" local="3500626666" remote="318763443893966832" Dst="-1" /><file name="RawContentEncoder.php" server="ftp.mercedesbenzmx.com" local="3500626666" remote="318763443893966832" Dst="-1" /><file name="Base64ContentEncoder.php" server="ftp.loop.mx/public_html/cms/" local="3500626666" remote="318763443920575992" Dst="-1" /><file name="NativeQpContentEncoder.php" server="ftp.loop.mx/public_html/cms/" local="3500626666" remote="318763443920575992" Dst="-1" /><file name="PlainContentEncoder.php" server="ftp.loop.mx/public_html/cms/" local="3500626666" remote="318763443920575992" Dst="-1" /><file name="QpContentEncoder.php" server="ftp.loop.mx/public_html/cms/" local="3500626666" remote="318763443920575992" Dst="-1" /><file name="QpContentEncoderProxy.php" server="ftp.loop.mx/public_html/cms/" local="3500626666" remote="318763443920575992" Dst="-1" /><file name="RawContentEncoder.php" server="ftp.loop.mx/public_html/cms/" local="3500626666" remote="318763443920575992" Dst="-1" /></dwsync>